typeconvert/func.py
typeconvert/utils.py
typeconvert/ufunc.py
typeconvert/typing.py
typeconvert/__init__.py
typeconvert/_c/milstd1750a48.c
typeconvert/_c/ufunc.cpython-313-i386-linux-gnu.so
typeconvert/_c/ibm64.c
typeconvert/_c/ti32.c
typeconvert/_c/dec64.c
typeconvert/_c/twoscomp.c
typeconvert/_c/ibm32.c
typeconvert/_c/dec32.c
typeconvert/_c/ti40.c
typeconvert/_c/dec64g.c
typeconvert/_c/bcd.c
typeconvert/_c/onescomp.c
typeconvert/_c/ufunc.c
typeconvert/_c/func.cpython-313-i386-linux-gnu.so
typeconvert/_c/func.c
typeconvert/_c/milstd1750a32.c
typeconvert/_c/utils.c
typeconvert/_c/__init__.py
typeconvert/_py/bcd.py
typeconvert/_py/milstd1750a48.py
typeconvert/_py/func.py
typeconvert/_py/dec64g.py
typeconvert/_py/twoscomp.py
typeconvert/_py/ti32.py
typeconvert/_py/dec32.py
typeconvert/_py/onescomp.py
typeconvert/_py/dec64.py
typeconvert/_py/ti40.py
typeconvert/_py/ibm32.py
typeconvert/_py/milstd1750a32.py
typeconvert/_py/ibm64.py
typeconvert/_py/ufunc.py
typeconvert/_py/__init__.py
typeconvert-1.0.0.dist-info/RECORD
typeconvert-1.0.0.dist-info/METADATA
typeconvert-1.0.0.dist-info/top_level.txt
typeconvert-1.0.0.dist-info/WHEEL
typeconvert-1.0.0.dist-info/licenses/LICENSE.md
