Metadata-Version: 2.4
Name: typeconvert
Version: 1.0.0
Summary: Add your description here
Project-URL: repository, https://github.com/jolsten/type-convert
Requires-Python: >=3.9
License-File: LICENSE.md
Requires-Dist: numpy>=2
Dynamic: license-file
